{
  "comment": "平板布局 - 8行网格（2025-01-06 重构）",
  "areas": [
    "C C C C W W W W",
    "C C C C W W W W",
    "C C C C W W W W",
    "C C C C W W W W",
    "A A A A N N T T",
    "A A A A N N T T",
    "A A A A N N T T",
    "A A A A N N T T"
  ],
  "tiles": {
    "C": {
      "type": "clock",
      "variant": "4x4",
      "comment": "时钟 - 4×4 大型版"
    },
    "W": {
      "type": "weather",
      "variant": "4x4",
      "comment": "天气 - 4×4 大型版"
    },
    "A": {
      "type": "calendar",
      "variant": "4x4",
      "comment": "日历 - 4×4 大型版"
    },
    "N": {
      "type": "news",
      "variant": "2x4",
      "comment": "新闻 - 2×4 高版（2列×4行）"
    },
    "T": {
      "type": "todo",
      "variant": "2x4",
      "comment": "待办 - 2×4 高版（2列×4行）"
    }
  }
}
